README.txt
VERSION.txt
setup.cfg
setup.py
docs/Makefile
docs/source/News.rst
docs/source/conf.py
docs/source/index.rst
docs/source/_static/logo_hi.gif
docs/source/_static/repoze.css
repoze/__init__.py
repoze.what.plugins.xml.egg-info/PKG-INFO
repoze.what.plugins.xml.egg-info/SOURCES.txt
repoze.what.plugins.xml.egg-info/dependency_links.txt
repoze.what.plugins.xml.egg-info/entry_points.txt
repoze.what.plugins.xml.egg-info/namespace_packages.txt
repoze.what.plugins.xml.egg-info/not-zip-safe
repoze.what.plugins.xml.egg-info/requires.txt
repoze.what.plugins.xml.egg-info/top_level.txt
repoze/what/__init__.py
repoze/what/plugins/__init__.py
repoze/what/plugins/xml/__init__.py
repoze/what/plugins/xml/adapters.py
tests/__init__.py
tests/test_adapters.py
tests/fixture/__init__.py
tests/fixture/groups.xml
tests/fixture/permissions.xml