Metadata-Version: 1.0
Name: repoze.what.plugins.xml
Version: 1.0b1-r2864
Summary: The repoze.what XML plugin
Home-page: http://code.gustavonarea.net/repoze.what.plugins.xml/
Author: Gustavo Narea
Author-email: repoze-dev@lists.repoze.org
License: BSD-derived (http://www.repoze.org/LICENSE.txt)
Keywords: web application server wsgi xml
Platform: UNKNOWN
Classifier: Development Status :: 4 - Beta
Classifier: Intended Audience :: Developers
Classifier: Programming Language :: Python
Classifier: Topic :: Text Processing :: Markup :: XML
